{
  "capture_health_status": {
    "captured": 0,
    "critical": 0,
    "expected_coverable": 35,
    "missing": 7,
    "provider_ok": true,
    "warning": 0
  },
  "counts": {
    "fixtures": 88,
    "picks": 40,
    "research": 122
  },
  "engine_commit": "8e76d12de9d24b3ab8c60027f8dbef267815eb18",
  "feed_commit": "22c41d1ee5891b5a732a8cc894ac107f4f66ca0d",
  "generated_at_utc": "2026-06-29T23:48:18.865138+00:00",
  "release_id": "20260629T234818Z-8e76d12-395b",
  "schema_version": "release_manifest.0",
  "schema_versions": {
    "capture_health": "capture_health.0",
    "closing_snapshot": "closing_snapshot.1",
    "clv": "clv.2",
    "feed_fixture": "feed_fixture.26",
    "feed_index": "feed_index.0",
    "picks_feed": "picks_feed.0"
  }
}
