{
  "fixture_key": "api_football:fixture:1489418",
  "form": {
    "away": {
      "matches": [
        {
          "away_score": 2,
          "away_team": "Austria",
          "date": "2025-11-15",
          "home_score": 0,
          "home_team": "Cyprus",
          "result": "W",
          "venue": "away"
        },
        {
          "away_score": 1,
          "away_team": "Bosnia and Herzegovina",
          "date": "2025-11-18",
          "home_score": 1,
          "home_team": "Austria",
          "result": "D",
          "venue": "home"
        },
        {
          "away_score": 1,
          "away_team": "Ghana",
          "date": "2026-03-27",
          "home_score": 5,
          "home_team": "Austria",
          "result": "W",
          "venue": "home"
        },
        {
          "away_score": 0,
          "away_team": "South Korea",
          "date": "2026-03-31",
          "home_score": 1,
          "home_team": "Austria",
          "result": "W",
          "venue": "home"
        },
        {
          "away_score": 0,
          "away_team": "Tunisia",
          "date": "2026-06-01",
          "home_score": 1,
          "home_team": "Austria",
          "result": "W",
          "venue": "home"
        }
      ],
      "summary": "WWWDW",
      "team_name": "Austria"
    },
    "execution_available": false,
    "fixture_key": "api_football:fixture:1489418",
    "h2h": {
      "away_wins": 1,
      "draws": 0,
      "home_wins": 0,
      "matches": [
        {
          "away_score": 2,
          "away_team": "Austria",
          "date": "1982-06-21",
          "home_score": 0,
          "home_team": "Algeria",
          "neutral": true
        }
      ]
    },
    "home": {
      "matches": [
        {
          "away_score": 0,
          "away_team": "DR Congo",
          "date": "2026-01-06",
          "home_score": 1,
          "home_team": "Algeria",
          "result": "W",
          "venue": "neutral"
        },
        {
          "away_score": 2,
          "away_team": "Nigeria",
          "date": "2026-01-10",
          "home_score": 0,
          "home_team": "Algeria",
          "result": "L",
          "venue": "neutral"
        },
        {
          "away_score": 0,
          "away_team": "Guatemala",
          "date": "2026-03-27",
          "home_score": 7,
          "home_team": "Algeria",
          "result": "W",
          "venue": "neutral"
        },
        {
          "away_score": 0,
          "away_team": "Uruguay",
          "date": "2026-03-31",
          "home_score": 0,
          "home_team": "Algeria",
          "result": "D",
          "venue": "neutral"
        },
        {
          "away_score": 1,
          "away_team": "Algeria",
          "date": "2026-06-03",
          "home_score": 0,
          "home_team": "Netherlands",
          "result": "W",
          "venue": "away"
        }
      ],
      "summary": "WDWLW",
      "team_name": "Algeria"
    },
    "last_n": 5,
    "operator_review_required": true,
    "output_status": "DISCOVERED",
    "proof_scope": "WORLD_CUP_FORM_CONTEXT",
    "results_through_date": "2026-06-03",
    "schema_version": "form.0",
    "source": "INTERNATIONAL_RESULTS_FORM"
  },
  "generated_at_utc": "2026-06-23T06:35:54.850758+00:00",
  "goals_projection": {
    "btts": {
      "no_probability": 0.457684927745861,
      "yes_probability": 0.5423150722541386
    },
    "execution_available": false,
    "fixture_key": "api_football:fixture:1489418",
    "market_type": "REGULATION_90_MIN_GOALS",
    "operator_review_required": true,
    "output_status": "DISCOVERED",
    "projection_label": "model projection \u00b7 tracked, not a bet",
    "proof_scope": "WORLD_CUP_GOALS_PROJECTION",
    "schema_version": "goals_projection.0",
    "source": "MODEL_GOALS_PROJECTION",
    "totals": [
      {
        "line": 1.5,
        "over_probability": 0.7459697865429138,
        "under_probability": 0.2540302134570859
      },
      {
        "line": 2.5,
        "over_probability": 0.4826401194195359,
        "under_probability": 0.5173598805804636
      },
      {
        "line": 3.5,
        "over_probability": 0.26492610315090925,
        "under_probability": 0.7350738968490901
      }
    ]
  },
  "h1_1x2": {
    "execution_available": false,
    "fixture_key": "api_football:fixture:1489418",
    "operator_review_required": true,
    "outcomes": [
      {
        "edge_pp": 0.019000000000000017,
        "kalshi_fair": 0.2261,
        "outcome": "home",
        "sharp_fair": 0.2451,
        "verdict": "NO_VALUE"
      },
      {
        "edge_pp": -0.019600000000000006,
        "kalshi_fair": 0.4874,
        "outcome": "draw",
        "sharp_fair": 0.4678,
        "verdict": "NO_VALUE"
      },
      {
        "edge_pp": 0.0006000000000000449,
        "kalshi_fair": 0.2865,
        "outcome": "away",
        "sharp_fair": 0.2871,
        "verdict": "NO_VALUE"
      }
    ],
    "output_status": "DISCOVERED",
    "period": "FIRST_HALF",
    "proof_scope": "WORLD_CUP_1H_1X2_COMPARISON",
    "schema_version": "h1_1x2.0",
    "source": "H1_1X2_COMPARISON"
  },
  "h1_1x2_kalshi": {
    "capture_timestamp_utc": "2026-06-23T06:35:59.310506+00:00",
    "de_vig_method": "proportional_kalshi",
    "execution_available": false,
    "fixture_key": "api_football:fixture:1489418",
    "market_anchor_probabilities": {
      "away": 0.2865,
      "draw": 0.4874,
      "home": 0.2261
    },
    "operator_review_required": true,
    "output_status": "DISCOVERED",
    "period": "FIRST_HALF",
    "proof_scope": "WORLD_CUP_1H_1X2_KALSHI_ANCHOR",
    "raw_prices_persisted": false,
    "request_cap": 1,
    "requests_attempted": 1,
    "requests_succeeded": 1,
    "schema_version": "h1_1x2_kalshi.0",
    "source": "KALSHI"
  },
  "h1_1x2_sharp": {
    "capture_timestamp_utc": "2026-06-23T06:35:56.708760+00:00",
    "de_vig_method": "proportional_pinnacle",
    "execution_available": false,
    "fixture_key": "api_football:fixture:1489418",
    "market_anchor_probabilities": {
      "away": 0.2871,
      "draw": 0.4678,
      "home": 0.2451
    },
    "operator_review_required": true,
    "output_status": "DISCOVERED",
    "period": "FIRST_HALF",
    "proof_scope": "WORLD_CUP_1H_1X2_SHARP_ANCHOR",
    "raw_prices_persisted": false,
    "request_cap": 1,
    "requests_attempted": 1,
    "requests_succeeded": 1,
    "schema_version": "h1_1x2_sharp.0",
    "source": "THE_ODDS_API"
  },
  "h1_spreads_kalshi": {
    "capture_timestamp_utc": "2026-06-23T06:35:59.310506+00:00",
    "de_vig_method": "proportional_kalshi",
    "execution_available": false,
    "fixture_key": "api_football:fixture:1489418",
    "lines": [
      {
        "away_cover_fair": 0.665,
        "home_cover_fair": 0.335,
        "line": -1.5
      },
      {
        "away_cover_fair": 0.07,
        "home_cover_fair": 0.93,
        "line": 1.5
      }
    ],
    "operator_review_required": true,
    "output_status": "DISCOVERED",
    "period": "FIRST_HALF",
    "proof_scope": "WORLD_CUP_1H_SPREADS_KALSHI_ANCHOR",
    "raw_prices_persisted": false,
    "request_cap": 1,
    "requests_attempted": 1,
    "requests_succeeded": 1,
    "schema_version": "h1_spreads_kalshi.0",
    "source": "KALSHI"
  },
  "h1_spreads_sharp": {
    "capture_timestamp_utc": "2026-06-23T06:35:56.708760+00:00",
    "de_vig_method": "proportional_pinnacle",
    "execution_available": false,
    "fixture_key": "api_football:fixture:1489418",
    "lines": [
      {
        "away_cover_fair": 0.5426,
        "home_cover_fair": 0.4574,
        "line": 0.0
      }
    ],
    "operator_review_required": true,
    "output_status": "DISCOVERED",
    "period": "FIRST_HALF",
    "proof_scope": "WORLD_CUP_1H_SPREADS_SHARP_ANCHOR",
    "raw_prices_persisted": false,
    "request_cap": 1,
    "requests_attempted": 1,
    "requests_succeeded": 1,
    "schema_version": "h1_spreads_sharp.0",
    "source": "THE_ODDS_API"
  },
  "h1_totals": {
    "execution_available": false,
    "fixture_key": "api_football:fixture:1489418",
    "operator_review_required": true,
    "output_status": "DISCOVERED",
    "period": "FIRST_HALF",
    "proof_scope": "WORLD_CUP_1H_TOTALS_COMPARISON",
    "schema_version": "h1_totals.0",
    "shared_lines": [
      {
        "kalshi_over_fair": 0.625,
        "line": 0.5,
        "over_edge_pp": -0.0026000000000000467,
        "sharp_over_fair": 0.6224
      }
    ],
    "source": "H1_TOTALS_COMPARISON"
  },
  "h1_totals_kalshi": {
    "capture_timestamp_utc": "2026-06-23T06:35:59.310506+00:00",
    "de_vig_method": "proportional_kalshi",
    "execution_available": false,
    "fixture_key": "api_football:fixture:1489418",
    "lines": [
      {
        "line": 0.5,
        "over_fair": 0.625,
        "under_fair": 0.375
      },
      {
        "line": 1.5,
        "over_fair": 0.27,
        "under_fair": 0.73
      },
      {
        "line": 2.5,
        "over_fair": 0.075,
        "under_fair": 0.925
      },
      {
        "line": 3.5,
        "over_fair": 0.02,
        "under_fair": 0.98
      }
    ],
    "operator_review_required": true,
    "output_status": "DISCOVERED",
    "period": "FIRST_HALF",
    "proof_scope": "WORLD_CUP_1H_TOTALS_KALSHI_ANCHOR",
    "raw_prices_persisted": false,
    "request_cap": 1,
    "requests_attempted": 1,
    "requests_succeeded": 1,
    "schema_version": "h1_totals_kalshi.0",
    "source": "KALSHI"
  },
  "h1_totals_sharp": {
    "capture_timestamp_utc": "2026-06-23T06:35:56.708760+00:00",
    "de_vig_method": "proportional_pinnacle",
    "execution_available": false,
    "fixture_key": "api_football:fixture:1489418",
    "lines": [
      {
        "line": 0.5,
        "over_fair": 0.6224,
        "under_fair": 0.3776
      },
      {
        "line": 0.75,
        "over_fair": 0.5416,
        "under_fair": 0.4584
      },
      {
        "line": 1.0,
        "over_fair": 0.4105,
        "under_fair": 0.5895
      },
      {
        "line": 1.25,
        "over_fair": 0.323,
        "under_fair": 0.677
      }
    ],
    "operator_review_required": true,
    "output_status": "DISCOVERED",
    "period": "FIRST_HALF",
    "proof_scope": "WORLD_CUP_1H_TOTALS_SHARP_ANCHOR",
    "raw_prices_persisted": false,
    "request_cap": 1,
    "requests_attempted": 1,
    "requests_succeeded": 1,
    "schema_version": "h1_totals_sharp.0",
    "source": "THE_ODDS_API"
  },
  "kalshi_anchor": {
    "capture_timestamp_utc": "2026-06-23T06:35:58.035653+00:00",
    "de_vig_method": "proportional_kalshi",
    "execution_available": false,
    "fixture_key": "api_football:fixture:1489418",
    "market_anchor_probabilities": {
      "away": 0.35323383084577115,
      "draw": 0.4029850746268657,
      "home": 0.2437810945273632
    },
    "market_type": "REGULATION_90_MIN_1X2",
    "operator_review_required": true,
    "output_status": "DISCOVERED",
    "proof_scope": "WORLD_CUP_KALSHI_DEVIGGED_ANCHOR",
    "provider": "KALSHI",
    "raw_prices_persisted": false,
    "schema_version": "kalshi_anchor.1",
    "source": "WORLD_CUP_KALSHI_DEVIGGED_ANCHOR"
  },
  "model_fairs": {
    "execution_available": false,
    "fixture_key": "api_football:fixture:1489418",
    "forms": {
      "ah_minus_0_25": {
        "away": 0.39839004599864375,
        "home": 0.43299687442461465
      },
      "ah_minus_1": {
        "away": 0.7838316627161979,
        "home": 0.21616833728380214,
        "push": 0.19692197480294799
      },
      "ah_minus_2": {
        "away": 0.9303841248492459,
        "home": 0.06961587515075417,
        "push": 0.11176476843056711
      },
      "dnb": {
        "away": 0.47918729079334493,
        "home": 0.5208127092066543
      },
      "double_chance": {
        "away": 0.6294779837810458,
        "home": 0.6590915736259456
      }
    },
    "model_probabilities": {
      "away": 0.34090842637405383,
      "draw": 0.2885695574069919,
      "home": 0.3705220162189537
    },
    "operator_review_required": true,
    "output_status": "DISCOVERED",
    "proof_scope": "WORLD_CUP_MODEL_FAIRS",
    "schema_version": "model_fairs.1",
    "source": "MODEL_DERIVED_FAIRS"
  },
  "proposal": {
    "blended_probabilities": {
      "away": 0.3535319135674689,
      "draw": 0.36447908905089077,
      "home": 0.2819889973816404
    },
    "confidence_tier": "LOW",
    "corroboration": "MODEL_ONLY",
    "execution_available": false,
    "fixture_key": "api_football:fixture:1489418",
    "kalshi_comparison": "COMPLETE",
    "kalshi_market_probabilities": {
      "away": 0.35323383084577115,
      "draw": 0.4029850746268657,
      "home": 0.2437810945273632
    },
    "kalshi_present": true,
    "market_type": "REGULATION_90_MIN_1X2",
    "min_edge": 0.02,
    "model_edges": {
      "away": -0.012325404471717316,
      "draw": -0.11441551721987381,
      "home": 0.12674092169159049
    },
    "model_probabilities": {
      "away": 0.34090842637405383,
      "draw": 0.2885695574069919,
      "home": 0.3705220162189537
    },
    "operator_review_required": true,
    "output_status": "REVIEW_READY",
    "pick_edge": 0.12674092169159049,
    "proof_scope": "WORLD_CUP_PICK_PROPOSAL",
    "recommended_pick": "home",
    "schema_version": "m1c.3",
    "sharp_edges": {
      "away": 0.0011661691542288466,
      "draw": 0.00331492537313427,
      "home": -0.0044810945273632
    },
    "sharp_market_probabilities": {
      "away": 0.3544,
      "draw": 0.4063,
      "home": 0.2393
    },
    "sharp_pick": "NO_VALUE",
    "sharp_pick_edge": 0.00331492537313427,
    "signal_strength": 1,
    "source": "MODEL_MARKET_PROPOSAL"
  },
  "release_id": "20260623T190037Z-f5a3dac-96fe",
  "schema_version": "feed_fixture.29",
  "scoreline_projection": {
    "execution_available": false,
    "fixture_key": "api_football:fixture:1489418",
    "market_type": "REGULATION_90_MIN_1X2",
    "operator_review_required": true,
    "output_status": "DISCOVERED",
    "projection_label": "model projection \u00b7 tracked, not a bet",
    "proof_scope": "WORLD_CUP_SCORELINE_PROJECTION",
    "schema_version": "scoreline_projection.0",
    "source": "MODEL_SCORELINE_PROJECTION",
    "top_scorelines": [
      {
        "away_goals": 1,
        "home_goals": 1,
        "probability": 0.13785708115371917
      },
      {
        "away_goals": 0,
        "home_goals": 0,
        "probability": 0.08649005774576222
      },
      {
        "away_goals": 0,
        "home_goals": 1,
        "probability": 0.08610922986852029
      }
    ],
    "top_scorelines_mass": 0.3104563687680017
  },
  "selection": {
    "draw_bridge_active": false,
    "draw_bridge_band": {
      "high": 0.6,
      "low": 0.475
    },
    "execution_available": false,
    "fixture_key": "api_football:fixture:1489418",
    "not_built": [
      "minus_1_5"
    ],
    "operator_review_required": true,
    "output_status": "DISCOVERED",
    "pick_book": null,
    "pick_corroboration": null,
    "pick_stars": null,
    "policy_version": "selection_policy.0",
    "proof_scope": "WORLD_CUP_RECOMMENDATION_FORM_SELECTION",
    "ranked_context": [
      {
        "corroboration": "SHARP_ONLY",
        "edge_pp": 0.005267812026275909,
        "form": "dnb",
        "line": null,
        "model_edge_pp": -0.11247937587332174,
        "side": "away",
        "status": "BELOW_THRESHOLD"
      },
      {
        "corroboration": "MODEL_ONLY",
        "edge_pp": -0.005267812026275964,
        "form": "dnb",
        "line": null,
        "model_edge_pp": 0.11247937587332091,
        "side": "home",
        "status": "BELOW_THRESHOLD"
      },
      {
        "corroboration": "SHARP_ONLY",
        "edge_pp": 0.0023836066349255947,
        "form": "ah_minus_0_25",
        "line": null,
        "model_edge_pp": -0.04397755524746216,
        "side": "away",
        "status": "BELOW_THRESHOLD"
      },
      {
        "corroboration": "MODEL_ONLY",
        "edge_pp": -0.004988489529547557,
        "form": "ah_minus_0_25",
        "line": null,
        "model_edge_pp": 0.12770092426885138,
        "side": "home",
        "status": "BELOW_THRESHOLD"
      },
      {
        "corroboration": "NO_MODEL_FAIR",
        "edge_pp": 0.009600000000000053,
        "form": "totals",
        "line": 1.5,
        "model_edge_pp": null,
        "side": "under",
        "status": "NOT_SURFACEABLE_OFF_MENU_LINE"
      },
      {
        "corroboration": "NO_MODEL_FAIR",
        "edge_pp": 0.006299999999999972,
        "form": "totals",
        "line": 2.5,
        "model_edge_pp": null,
        "side": "over",
        "status": "NOT_SURFACEABLE_LONGSHOT"
      },
      {
        "corroboration": "NO_MODEL_FAIR",
        "edge_pp": -0.006299999999999972,
        "form": "totals",
        "line": 2.5,
        "model_edge_pp": null,
        "side": "under",
        "status": "BELOW_THRESHOLD"
      },
      {
        "corroboration": "NO_MODEL_FAIR",
        "edge_pp": -0.009600000000000053,
        "form": "totals",
        "line": 1.5,
        "model_edge_pp": null,
        "side": "over",
        "status": "NOT_SURFACEABLE_OFF_MENU_LINE"
      },
      {
        "corroboration": "SHARP_ONLY",
        "edge_pp": 0.00331492537313427,
        "form": "one_x_two",
        "line": null,
        "model_edge_pp": -0.11441551721987381,
        "side": "draw",
        "status": "BELOW_THRESHOLD"
      },
      {
        "corroboration": "SHARP_ONLY",
        "edge_pp": 0.0011661691542288466,
        "form": "one_x_two",
        "line": null,
        "model_edge_pp": -0.012325404471717316,
        "side": "away",
        "status": "BELOW_THRESHOLD"
      },
      {
        "corroboration": "MODEL_ONLY",
        "edge_pp": -0.0044810945273632,
        "form": "one_x_two",
        "line": null,
        "model_edge_pp": 0.12674092169159049,
        "side": "home",
        "status": "BELOW_THRESHOLD"
      },
      {
        "corroboration": "SHARP_ONLY",
        "edge_pp": 0.004481094527363005,
        "form": "double_chance",
        "line": null,
        "model_edge_pp": -0.12674092169159112,
        "side": "away",
        "status": "BELOW_THRESHOLD"
      },
      {
        "corroboration": "SHARP_ONLY",
        "edge_pp": -0.0011661691542289576,
        "form": "double_chance",
        "line": null,
        "model_edge_pp": 0.012325404471716706,
        "side": "home",
        "status": "BELOW_THRESHOLD"
      },
      {
        "corroboration": "NO_MODEL_FAIR",
        "edge_pp": 0.019000000000000017,
        "form": "h1_one_x_two",
        "line": null,
        "model_edge_pp": null,
        "side": "home",
        "status": "BELOW_THRESHOLD"
      },
      {
        "corroboration": "NO_MODEL_FAIR",
        "edge_pp": 0.0006000000000000449,
        "form": "h1_one_x_two",
        "line": null,
        "model_edge_pp": null,
        "side": "away",
        "status": "BELOW_THRESHOLD"
      },
      {
        "corroboration": "NO_MODEL_FAIR",
        "edge_pp": -0.019600000000000006,
        "form": "h1_one_x_two",
        "line": null,
        "model_edge_pp": null,
        "side": "draw",
        "status": "BELOW_THRESHOLD"
      },
      {
        "corroboration": "NO_MODEL_FAIR",
        "edge_pp": 0.0026000000000000467,
        "form": "h1_totals",
        "line": 0.5,
        "model_edge_pp": null,
        "side": "under",
        "status": "NOT_SURFACEABLE_CONTEXT_ONLY"
      },
      {
        "corroboration": "NO_MODEL_FAIR",
        "edge_pp": -0.0026000000000000467,
        "form": "h1_totals",
        "line": 0.5,
        "model_edge_pp": null,
        "side": "over",
        "status": "NOT_SURFACEABLE_CONTEXT_ONLY"
      }
    ],
    "schema_version": "selection.6",
    "selected_edge_pp": null,
    "selected_form": null,
    "selected_line": null,
    "selected_reason": "NO_FORM_CLEARS",
    "selected_side": null,
    "selection_status": "NO_VALUE",
    "source": "SELECTION_POLICY",
    "threshold_pp": 0.02
  },
  "sharp_anchor": {
    "bookmaker_count": 1,
    "bookmaker_set_used": [
      "pinnacle"
    ],
    "capture_timestamp_utc": "2026-06-23T06:35:55.464930+00:00",
    "de_vig_method": "proportional_pinnacle",
    "execution_available": false,
    "fixture_key": "api_football:fixture:1489418",
    "market_anchor_probabilities": {
      "away": 0.3544,
      "draw": 0.4063,
      "home": 0.2393
    },
    "market_type": "REGULATION_90_MIN_1X2",
    "operator_review_required": true,
    "output_status": "DISCOVERED",
    "proof_scope": "WORLD_CUP_DEVIGGED_MARKET_ANCHOR",
    "provider": "THE_ODDS_API",
    "raw_prices_persisted": false,
    "request_cap": 1,
    "requests_attempted": 1,
    "requests_succeeded": 1,
    "schema_version": "o1.0",
    "sport_key": "soccer_fifa_world_cup"
  },
  "softbook_1x2": {
    "benchmark": {
      "book": "pinnacle",
      "probabilities": {
        "away": 0.3544,
        "draw": 0.4063,
        "home": 0.2393
      }
    },
    "books": [
      {
        "actionability": "syndicate_only",
        "book_key": "betclic_fr",
        "edge_pp": {
          "away": 0.0042999999999999705,
          "draw": 0.007099999999999995,
          "home": -0.011399999999999966
        },
        "probabilities": {
          "away": 0.3501,
          "draw": 0.3992,
          "home": 0.2507
        },
        "verdict": {
          "away": "NO_VALUE",
          "draw": "NO_VALUE",
          "home": "NO_VALUE"
        }
      },
      {
        "actionability": "directly_actionable",
        "book_key": "betfair_ex_au",
        "edge_pp": {
          "away": 0.008000000000000007,
          "draw": 0.003500000000000003,
          "home": -0.01150000000000001
        },
        "probabilities": {
          "away": 0.3464,
          "draw": 0.4028,
          "home": 0.2508
        },
        "verdict": {
          "away": "NO_VALUE",
          "draw": "NO_VALUE",
          "home": "NO_VALUE"
        }
      },
      {
        "actionability": "directly_actionable",
        "book_key": "betfair_ex_eu",
        "edge_pp": {
          "away": 0.008000000000000007,
          "draw": 0.003500000000000003,
          "home": -0.01150000000000001
        },
        "probabilities": {
          "away": 0.3464,
          "draw": 0.4028,
          "home": 0.2508
        },
        "verdict": {
          "away": "NO_VALUE",
          "draw": "NO_VALUE",
          "home": "NO_VALUE"
        }
      },
      {
        "actionability": "directly_actionable",
        "book_key": "betfair_ex_uk",
        "edge_pp": {
          "away": 0.008000000000000007,
          "draw": 0.003500000000000003,
          "home": -0.01150000000000001
        },
        "probabilities": {
          "away": 0.3464,
          "draw": 0.4028,
          "home": 0.2508
        },
        "verdict": {
          "away": "NO_VALUE",
          "draw": "NO_VALUE",
          "home": "NO_VALUE"
        }
      },
      {
        "actionability": "syndicate_only",
        "book_key": "betfred_uk",
        "edge_pp": {
          "away": 0.017500000000000016,
          "draw": 0.02899999999999997,
          "home": -0.046499999999999986
        },
        "probabilities": {
          "away": 0.3369,
          "draw": 0.3773,
          "home": 0.2858
        },
        "verdict": {
          "away": "NO_VALUE",
          "draw": "VALUE",
          "home": "NO_VALUE"
        }
      },
      {
        "actionability": "syndicate_only",
        "book_key": "betmgm",
        "edge_pp": {
          "away": 0.0,
          "draw": 0.021199999999999997,
          "home": -0.021199999999999997
        },
        "probabilities": {
          "away": 0.3544,
          "draw": 0.3851,
          "home": 0.2605
        },
        "verdict": {
          "away": "NO_VALUE",
          "draw": "VALUE",
          "home": "NO_VALUE"
        }
      },
      {
        "actionability": "syndicate_only",
        "book_key": "betonlineag",
        "edge_pp": {
          "away": 0.008000000000000007,
          "draw": 0.003699999999999981,
          "home": -0.011699999999999988
        },
        "probabilities": {
          "away": 0.3464,
          "draw": 0.4026,
          "home": 0.251
        },
        "verdict": {
          "away": "NO_VALUE",
          "draw": "NO_VALUE",
          "home": "NO_VALUE"
        }
      },
      {
        "actionability": "syndicate_only",
        "book_key": "betright",
        "edge_pp": {
          "away": 0.012399999999999967,
          "draw": 0.004799999999999971,
          "home": -0.017199999999999993
        },
        "probabilities": {
          "away": 0.342,
          "draw": 0.4015,
          "home": 0.2565
        },
        "verdict": {
          "away": "NO_VALUE",
          "draw": "NO_VALUE",
          "home": "NO_VALUE"
        }
      },
      {
        "actionability": "syndicate_only",
        "book_key": "betrivers",
        "edge_pp": {
          "away": -0.0010999999999999899,
          "draw": 0.011199999999999988,
          "home": -0.010099999999999998
        },
        "probabilities": {
          "away": 0.3555,
          "draw": 0.3951,
          "home": 0.2494
        },
        "verdict": {
          "away": "NO_VALUE",
          "draw": "NO_VALUE",
          "home": "NO_VALUE"
        }
      },
      {
        "actionability": "syndicate_only",
        "book_key": "betway",
        "edge_pp": {
          "away": -0.011099999999999999,
          "draw": 0.02560000000000001,
          "home": -0.014500000000000013
        },
        "probabilities": {
          "away": 0.3655,
          "draw": 0.3807,
          "home": 0.2538
        },
        "verdict": {
          "away": "NO_VALUE",
          "draw": "VALUE",
          "home": "NO_VALUE"
        }
      },
      {
        "actionability": "syndicate_only",
        "book_key": "boylesports",
        "edge_pp": {
          "away": -0.01479999999999998,
          "draw": 0.021699999999999997,
          "home": -0.0068999999999999895
        },
        "probabilities": {
          "away": 0.3692,
          "draw": 0.3846,
          "home": 0.2462
        },
        "verdict": {
          "away": "NO_VALUE",
          "draw": "VALUE",
          "home": "NO_VALUE"
        }
      },
      {
        "actionability": "syndicate_only",
        "book_key": "casumo",
        "edge_pp": {
          "away": -0.0010999999999999899,
          "draw": 0.011199999999999988,
          "home": -0.010099999999999998
        },
        "probabilities": {
          "away": 0.3555,
          "draw": 0.3951,
          "home": 0.2494
        },
        "verdict": {
          "away": "NO_VALUE",
          "draw": "NO_VALUE",
          "home": "NO_VALUE"
        }
      },
      {
        "actionability": "syndicate_only",
        "book_key": "codere_it",
        "edge_pp": {
          "away": 0.0017999999999999683,
          "draw": 0.006199999999999983,
          "home": -0.00799999999999998
        },
        "probabilities": {
          "away": 0.3526,
          "draw": 0.4001,
          "home": 0.2473
        },
        "verdict": {
          "away": "NO_VALUE",
          "draw": "NO_VALUE",
          "home": "NO_VALUE"
        }
      },
      {
        "actionability": "syndicate_only",
        "book_key": "coral",
        "edge_pp": {
          "away": 0.0040999999999999925,
          "draw": 0.012199999999999989,
          "home": -0.01629999999999998
        },
        "probabilities": {
          "away": 0.3503,
          "draw": 0.3941,
          "home": 0.2556
        },
        "verdict": {
          "away": "NO_VALUE",
          "draw": "NO_VALUE",
          "home": "NO_VALUE"
        }
      },
      {
        "actionability": "syndicate_only",
        "book_key": "dabble_au",
        "edge_pp": {
          "away": 0.018899999999999972,
          "draw": 0.005299999999999971,
          "home": -0.0242
        },
        "probabilities": {
          "away": 0.3355,
          "draw": 0.401,
          "home": 0.2635
        },
        "verdict": {
          "away": "NO_VALUE",
          "draw": "NO_VALUE",
          "home": "NO_VALUE"
        }
      },
      {
        "actionability": "syndicate_only",
        "book_key": "draftkings",
        "edge_pp": {
          "away": -0.006599999999999995,
          "draw": 0.01579999999999998,
          "home": -0.009199999999999986
        },
        "probabilities": {
          "away": 0.361,
          "draw": 0.3905,
          "home": 0.2485
        },
        "verdict": {
          "away": "NO_VALUE",
          "draw": "NO_VALUE",
          "home": "NO_VALUE"
        }
      },
      {
        "actionability": "syndicate_only",
        "book_key": "everygame",
        "edge_pp": {
          "away": 0.00029999999999996696,
          "draw": -0.0005999999999999894,
          "home": 0.00030000000000002247
        },
        "probabilities": {
          "away": 0.3541,
          "draw": 0.4069,
          "home": 0.239
        },
        "verdict": {
          "away": "NO_VALUE",
          "draw": "NO_VALUE",
          "home": "NO_VALUE"
        }
      },
      {
        "actionability": "syndicate_only",
        "book_key": "fanatics",
        "edge_pp": {
          "away": -0.007000000000000006,
          "draw": 0.014899999999999969,
          "home": -0.00789999999999999
        },
        "probabilities": {
          "away": 0.3614,
          "draw": 0.3914,
          "home": 0.2472
        },
        "verdict": {
          "away": "NO_VALUE",
          "draw": "NO_VALUE",
          "home": "NO_VALUE"
        }
      },
      {
        "actionability": "syndicate_only",
        "book_key": "fanduel",
        "edge_pp": {
          "away": 0.011199999999999988,
          "draw": 0.004599999999999993,
          "home": -0.01579999999999998
        },
        "probabilities": {
          "away": 0.3432,
          "draw": 0.4017,
          "home": 0.2551
        },
        "verdict": {
          "away": "NO_VALUE",
          "draw": "NO_VALUE",
          "home": "NO_VALUE"
        }
      },
      {
        "actionability": "syndicate_only",
        "book_key": "grosvenor",
        "edge_pp": {
          "away": 0.00269999999999998,
          "draw": 0.009799999999999975,
          "home": -0.012500000000000011
        },
        "probabilities": {
          "away": 0.3517,
          "draw": 0.3965,
          "home": 0.2518
        },
        "verdict": {
          "away": "NO_VALUE",
          "draw": "NO_VALUE",
          "home": "NO_VALUE"
        }
      },
      {
        "actionability": "syndicate_only",
        "book_key": "gtbets",
        "edge_pp": {
          "away": -0.017199999999999993,
          "draw": 0.03889999999999999,
          "home": -0.021699999999999997
        },
        "probabilities": {
          "away": 0.3716,
          "draw": 0.3674,
          "home": 0.261
        },
        "verdict": {
          "away": "NO_VALUE",
          "draw": "VALUE",
          "home": "NO_VALUE"
        }
      },
      {
        "actionability": "syndicate_only",
        "book_key": "ladbrokes_au",
        "edge_pp": {
          "away": -0.00020000000000003348,
          "draw": 0.01479999999999998,
          "home": -0.014600000000000002
        },
        "probabilities": {
          "away": 0.3546,
          "draw": 0.3915,
          "home": 0.2539
        },
        "verdict": {
          "away": "NO_VALUE",
          "draw": "NO_VALUE",
          "home": "NO_VALUE"
        }
      },
      {
        "actionability": "syndicate_only",
        "book_key": "ladbrokes_uk",
        "edge_pp": {
          "away": -0.0028000000000000247,
          "draw": 0.01639999999999997,
          "home": -0.013600000000000001
        },
        "probabilities": {
          "away": 0.3572,
          "draw": 0.3899,
          "home": 0.2529
        },
        "verdict": {
          "away": "NO_VALUE",
          "draw": "NO_VALUE",
          "home": "NO_VALUE"
        }
      },
      {
        "actionability": "syndicate_only",
        "book_key": "leovegas",
        "edge_pp": {
          "away": -0.0010999999999999899,
          "draw": 0.011199999999999988,
          "home": -0.010099999999999998
        },
        "probabilities": {
          "away": 0.3555,
          "draw": 0.3951,
          "home": 0.2494
        },
        "verdict": {
          "away": "NO_VALUE",
          "draw": "NO_VALUE",
          "home": "NO_VALUE"
        }
      },
      {
        "actionability": "syndicate_only",
        "book_key": "leovegas_se",
        "edge_pp": {
          "away": -0.0010999999999999899,
          "draw": 0.011199999999999988,
          "home": -0.010099999999999998
        },
        "probabilities": {
          "away": 0.3555,
          "draw": 0.3951,
          "home": 0.2494
        },
        "verdict": {
          "away": "NO_VALUE",
          "draw": "NO_VALUE",
          "home": "NO_VALUE"
        }
      },
      {
        "actionability": "syndicate_only",
        "book_key": "livescorebet",
        "edge_pp": {
          "away": 0.00269999999999998,
          "draw": 0.009799999999999975,
          "home": -0.012500000000000011
        },
        "probabilities": {
          "away": 0.3517,
          "draw": 0.3965,
          "home": 0.2518
        },
        "verdict": {
          "away": "NO_VALUE",
          "draw": "NO_VALUE",
          "home": "NO_VALUE"
        }
      },
      {
        "actionability": "syndicate_only",
        "book_key": "lowvig",
        "edge_pp": {
          "away": 0.008000000000000007,
          "draw": 0.003699999999999981,
          "home": -0.011699999999999988
        },
        "probabilities": {
          "away": 0.3464,
          "draw": 0.4026,
          "home": 0.251
        },
        "verdict": {
          "away": "NO_VALUE",
          "draw": "NO_VALUE",
          "home": "NO_VALUE"
        }
      },
      {
        "actionability": "syndicate_only",
        "book_key": "marathonbet",
        "edge_pp": {
          "away": -0.007900000000000018,
          "draw": 0.02529999999999999,
          "home": -0.01739999999999997
        },
        "probabilities": {
          "away": 0.3623,
          "draw": 0.381,
          "home": 0.2567
        },
        "verdict": {
          "away": "NO_VALUE",
          "draw": "VALUE",
          "home": "NO_VALUE"
        }
      },
      {
        "actionability": "directly_actionable",
        "book_key": "matchbook",
        "edge_pp": {
          "away": 0.006799999999999973,
          "draw": 0.005500000000000005,
          "home": -0.012299999999999978
        },
        "probabilities": {
          "away": 0.3476,
          "draw": 0.4008,
          "home": 0.2516
        },
        "verdict": {
          "away": "NO_VALUE",
          "draw": "NO_VALUE",
          "home": "NO_VALUE"
        }
      },
      {
        "actionability": "syndicate_only",
        "book_key": "mybookieag",
        "edge_pp": {
          "away": 0.0032999999999999696,
          "draw": 0.006000000000000005,
          "home": -0.009299999999999975
        },
        "probabilities": {
          "away": 0.3511,
          "draw": 0.4003,
          "home": 0.2486
        },
        "verdict": {
          "away": "NO_VALUE",
          "draw": "NO_VALUE",
          "home": "NO_VALUE"
        }
      },
      {
        "actionability": "syndicate_only",
        "book_key": "neds",
        "edge_pp": {
          "away": -0.00020000000000003348,
          "draw": 0.01479999999999998,
          "home": -0.014600000000000002
        },
        "probabilities": {
          "away": 0.3546,
          "draw": 0.3915,
          "home": 0.2539
        },
        "verdict": {
          "away": "NO_VALUE",
          "draw": "NO_VALUE",
          "home": "NO_VALUE"
        }
      },
      {
        "actionability": "syndicate_only",
        "book_key": "onexbet",
        "edge_pp": {
          "away": -0.007300000000000029,
          "draw": 0.024899999999999978,
          "home": -0.017600000000000005
        },
        "probabilities": {
          "away": 0.3617,
          "draw": 0.3814,
          "home": 0.2569
        },
        "verdict": {
          "away": "NO_VALUE",
          "draw": "VALUE",
          "home": "NO_VALUE"
        }
      },
      {
        "actionability": "syndicate_only",
        "book_key": "paddypower",
        "edge_pp": {
          "away": 0.010000000000000009,
          "draw": 0.0020000000000000018,
          "home": -0.01200000000000001
        },
        "probabilities": {
          "away": 0.3444,
          "draw": 0.4043,
          "home": 0.2513
        },
        "verdict": {
          "away": "NO_VALUE",
          "draw": "NO_VALUE",
          "home": "NO_VALUE"
        }
      },
      {
        "actionability": "syndicate_only",
        "book_key": "playup",
        "edge_pp": {
          "away": 0.017699999999999994,
          "draw": 0.00379999999999997,
          "home": -0.021499999999999964
        },
        "probabilities": {
          "away": 0.3367,
          "draw": 0.4025,
          "home": 0.2608
        },
        "verdict": {
          "away": "NO_VALUE",
          "draw": "NO_VALUE",
          "home": "NO_VALUE"
        }
      },
      {
        "actionability": "syndicate_only",
        "book_key": "pmu_fr",
        "edge_pp": {
          "away": 0.00269999999999998,
          "draw": 0.009799999999999975,
          "home": -0.012500000000000011
        },
        "probabilities": {
          "away": 0.3517,
          "draw": 0.3965,
          "home": 0.2518
        },
        "verdict": {
          "away": "NO_VALUE",
          "draw": "NO_VALUE",
          "home": "NO_VALUE"
        }
      },
      {
        "actionability": "syndicate_only",
        "book_key": "pointsbetau",
        "edge_pp": {
          "away": -0.007000000000000006,
          "draw": 0.014899999999999969,
          "home": -0.00789999999999999
        },
        "probabilities": {
          "away": 0.3614,
          "draw": 0.3914,
          "home": 0.2472
        },
        "verdict": {
          "away": "NO_VALUE",
          "draw": "NO_VALUE",
          "home": "NO_VALUE"
        }
      },
      {
        "actionability": "syndicate_only",
        "book_key": "skybet",
        "edge_pp": {
          "away": 0.012399999999999967,
          "draw": 0.004799999999999971,
          "home": -0.017199999999999993
        },
        "probabilities": {
          "away": 0.342,
          "draw": 0.4015,
          "home": 0.2565
        },
        "verdict": {
          "away": "NO_VALUE",
          "draw": "NO_VALUE",
          "home": "NO_VALUE"
        }
      },
      {
        "actionability": "directly_actionable",
        "book_key": "smarkets",
        "edge_pp": {
          "away": 0.008000000000000007,
          "draw": 0.006799999999999973,
          "home": -0.01479999999999998
        },
        "probabilities": {
          "away": 0.3464,
          "draw": 0.3995,
          "home": 0.2541
        },
        "verdict": {
          "away": "NO_VALUE",
          "draw": "NO_VALUE",
          "home": "NO_VALUE"
        }
      },
      {
        "actionability": "syndicate_only",
        "book_key": "sport888",
        "edge_pp": {
          "away": 0.008099999999999996,
          "draw": 0.011799999999999977,
          "home": -0.019899999999999973
        },
        "probabilities": {
          "away": 0.3463,
          "draw": 0.3945,
          "home": 0.2592
        },
        "verdict": {
          "away": "NO_VALUE",
          "draw": "NO_VALUE",
          "home": "NO_VALUE"
        }
      },
      {
        "actionability": "syndicate_only",
        "book_key": "sportsbet",
        "edge_pp": {
          "away": 0.005900000000000016,
          "draw": 0.007000000000000006,
          "home": -0.012899999999999967
        },
        "probabilities": {
          "away": 0.3485,
          "draw": 0.3993,
          "home": 0.2522
        },
        "verdict": {
          "away": "NO_VALUE",
          "draw": "NO_VALUE",
          "home": "NO_VALUE"
        }
      },
      {
        "actionability": "syndicate_only",
        "book_key": "tab",
        "edge_pp": {
          "away": 0.020600000000000007,
          "draw": -0.00019999999999997797,
          "home": -0.020399999999999974
        },
        "probabilities": {
          "away": 0.3338,
          "draw": 0.4065,
          "home": 0.2597
        },
        "verdict": {
          "away": "VALUE",
          "draw": "NO_VALUE",
          "home": "NO_VALUE"
        }
      },
      {
        "actionability": "syndicate_only",
        "book_key": "tabtouch",
        "edge_pp": {
          "away": 0.00269999999999998,
          "draw": 0.009799999999999975,
          "home": -0.012500000000000011
        },
        "probabilities": {
          "away": 0.3517,
          "draw": 0.3965,
          "home": 0.2518
        },
        "verdict": {
          "away": "NO_VALUE",
          "draw": "NO_VALUE",
          "home": "NO_VALUE"
        }
      },
      {
        "actionability": "syndicate_only",
        "book_key": "tipico_de",
        "edge_pp": {
          "away": -0.02429999999999999,
          "draw": 0.027700000000000002,
          "home": -0.0033999999999999864
        },
        "probabilities": {
          "away": 0.3787,
          "draw": 0.3786,
          "home": 0.2427
        },
        "verdict": {
          "away": "NO_VALUE",
          "draw": "VALUE",
          "home": "NO_VALUE"
        }
      },
      {
        "actionability": "syndicate_only",
        "book_key": "unibet",
        "edge_pp": {
          "away": -0.0010999999999999899,
          "draw": 0.011199999999999988,
          "home": -0.010099999999999998
        },
        "probabilities": {
          "away": 0.3555,
          "draw": 0.3951,
          "home": 0.2494
        },
        "verdict": {
          "away": "NO_VALUE",
          "draw": "NO_VALUE",
          "home": "NO_VALUE"
        }
      },
      {
        "actionability": "syndicate_only",
        "book_key": "unibet_fr",
        "edge_pp": {
          "away": -0.016000000000000014,
          "draw": 0.020399999999999974,
          "home": -0.004399999999999987
        },
        "probabilities": {
          "away": 0.3704,
          "draw": 0.3859,
          "home": 0.2437
        },
        "verdict": {
          "away": "NO_VALUE",
          "draw": "VALUE",
          "home": "NO_VALUE"
        }
      },
      {
        "actionability": "syndicate_only",
        "book_key": "unibet_nl",
        "edge_pp": {
          "away": -0.0010999999999999899,
          "draw": 0.011199999999999988,
          "home": -0.010099999999999998
        },
        "probabilities": {
          "away": 0.3555,
          "draw": 0.3951,
          "home": 0.2494
        },
        "verdict": {
          "away": "NO_VALUE",
          "draw": "NO_VALUE",
          "home": "NO_VALUE"
        }
      },
      {
        "actionability": "syndicate_only",
        "book_key": "unibet_se",
        "edge_pp": {
          "away": -0.0010999999999999899,
          "draw": 0.011199999999999988,
          "home": -0.010099999999999998
        },
        "probabilities": {
          "away": 0.3555,
          "draw": 0.3951,
          "home": 0.2494
        },
        "verdict": {
          "away": "NO_VALUE",
          "draw": "NO_VALUE",
          "home": "NO_VALUE"
        }
      },
      {
        "actionability": "syndicate_only",
        "book_key": "unibet_uk",
        "edge_pp": {
          "away": 0.0029000000000000137,
          "draw": 0.007500000000000007,
          "home": -0.010399999999999993
        },
        "probabilities": {
          "away": 0.3515,
          "draw": 0.3988,
          "home": 0.2497
        },
        "verdict": {
          "away": "NO_VALUE",
          "draw": "NO_VALUE",
          "home": "NO_VALUE"
        }
      },
      {
        "actionability": "syndicate_only",
        "book_key": "virginbet",
        "edge_pp": {
          "away": 0.00269999999999998,
          "draw": 0.009799999999999975,
          "home": -0.012500000000000011
        },
        "probabilities": {
          "away": 0.3517,
          "draw": 0.3965,
          "home": 0.2518
        },
        "verdict": {
          "away": "NO_VALUE",
          "draw": "NO_VALUE",
          "home": "NO_VALUE"
        }
      },
      {
        "actionability": "syndicate_only",
        "book_key": "williamhill",
        "edge_pp": {
          "away": 0.008099999999999996,
          "draw": 0.011799999999999977,
          "home": -0.019899999999999973
        },
        "probabilities": {
          "away": 0.3463,
          "draw": 0.3945,
          "home": 0.2592
        },
        "verdict": {
          "away": "NO_VALUE",
          "draw": "NO_VALUE",
          "home": "NO_VALUE"
        }
      },
      {
        "actionability": "syndicate_only",
        "book_key": "winamax_de",
        "edge_pp": {
          "away": -0.0013000000000000234,
          "draw": 0.019699999999999995,
          "home": -0.018399999999999972
        },
        "probabilities": {
          "away": 0.3557,
          "draw": 0.3866,
          "home": 0.2577
        },
        "verdict": {
          "away": "NO_VALUE",
          "draw": "NO_VALUE",
          "home": "NO_VALUE"
        }
      },
      {
        "actionability": "syndicate_only",
        "book_key": "winamax_fr",
        "edge_pp": {
          "away": -0.00040000000000001146,
          "draw": 0.019199999999999995,
          "home": -0.018799999999999983
        },
        "probabilities": {
          "away": 0.3548,
          "draw": 0.3871,
          "home": 0.2581
        },
        "verdict": {
          "away": "NO_VALUE",
          "draw": "NO_VALUE",
          "home": "NO_VALUE"
        }
      }
    ],
    "capture_timestamp_utc": "2026-06-23T06:35:56.844394+00:00",
    "consensus": {
      "away": 0.3522,
      "draw": 0.3956,
      "home": 0.2522
    },
    "de_vig_method": "proportional",
    "execution_available": false,
    "fixture_key": "api_football:fixture:1489418",
    "operator_review_required": true,
    "output_status": "DISCOVERED",
    "period": "FULL_MATCH",
    "proof_scope": "WORLD_CUP_SOFTBOOK_1X2",
    "raw_prices_persisted": false,
    "request_cap": 1,
    "requests_attempted": 1,
    "requests_succeeded": 1,
    "schema_version": "softbook_1x2.2",
    "source": "THE_ODDS_API"
  },
  "softbook_signals": {
    "execution_available": false,
    "fixture_key": "api_football:fixture:1489418",
    "operator_review_required": true,
    "output_status": "DISCOVERED",
    "proof_scope": "WORLD_CUP_SOFTBOOK_SIGNALS",
    "recommendation_eligible": [],
    "research_signal": [
      {
        "actionability": "syndicate_only",
        "book_key": "paddypower",
        "edge_pp": 0.048699999999999966,
        "line": 2.5,
        "market": "totals",
        "side": "under"
      },
      {
        "actionability": "syndicate_only",
        "book_key": "gtbets",
        "edge_pp": 0.03889999999999999,
        "line": null,
        "market": "one_x_two",
        "side": "draw"
      },
      {
        "actionability": "syndicate_only",
        "book_key": "paddypower",
        "edge_pp": 0.03570000000000001,
        "line": 1.5,
        "market": "totals",
        "side": "under"
      },
      {
        "actionability": "syndicate_only",
        "book_key": "tab",
        "edge_pp": 0.03420000000000001,
        "line": 0.0,
        "market": "spreads",
        "side": "away"
      },
      {
        "actionability": "syndicate_only",
        "book_key": "fanduel",
        "edge_pp": 0.02939999999999998,
        "line": 1.5,
        "market": "totals",
        "side": "under"
      },
      {
        "actionability": "syndicate_only",
        "book_key": "betfred_uk",
        "edge_pp": 0.02899999999999997,
        "line": null,
        "market": "one_x_two",
        "side": "draw"
      },
      {
        "actionability": "syndicate_only",
        "book_key": "tipico_de",
        "edge_pp": 0.027700000000000002,
        "line": null,
        "market": "one_x_two",
        "side": "draw"
      },
      {
        "actionability": "syndicate_only",
        "book_key": "betway",
        "edge_pp": 0.02560000000000001,
        "line": null,
        "market": "one_x_two",
        "side": "draw"
      },
      {
        "actionability": "syndicate_only",
        "book_key": "marathonbet",
        "edge_pp": 0.02529999999999999,
        "line": null,
        "market": "one_x_two",
        "side": "draw"
      },
      {
        "actionability": "syndicate_only",
        "book_key": "onexbet",
        "edge_pp": 0.024899999999999978,
        "line": null,
        "market": "one_x_two",
        "side": "draw"
      },
      {
        "actionability": "syndicate_only",
        "book_key": "mybookieag",
        "edge_pp": 0.0247,
        "line": 2.0,
        "market": "totals",
        "side": "under"
      },
      {
        "actionability": "syndicate_only",
        "book_key": "playup",
        "edge_pp": 0.02429999999999999,
        "line": 2.5,
        "market": "totals",
        "side": "under"
      },
      {
        "actionability": "syndicate_only",
        "book_key": "tab",
        "edge_pp": 0.02429999999999999,
        "line": 2.5,
        "market": "totals",
        "side": "under"
      },
      {
        "actionability": "syndicate_only",
        "book_key": "codere_it",
        "edge_pp": 0.02400000000000002,
        "line": 2.5,
        "market": "totals",
        "side": "under"
      },
      {
        "actionability": "syndicate_only",
        "book_key": "tab",
        "edge_pp": 0.023099999999999954,
        "line": 0.5,
        "market": "spreads",
        "side": "away"
      },
      {
        "actionability": "syndicate_only",
        "book_key": "onexbet",
        "edge_pp": 0.02180000000000004,
        "line": 1.5,
        "market": "totals",
        "side": "over"
      },
      {
        "actionability": "syndicate_only",
        "book_key": "boylesports",
        "edge_pp": 0.021699999999999997,
        "line": null,
        "market": "one_x_two",
        "side": "draw"
      },
      {
        "actionability": "syndicate_only",
        "book_key": "betmgm",
        "edge_pp": 0.021199999999999997,
        "line": null,
        "market": "one_x_two",
        "side": "draw"
      },
      {
        "actionability": "syndicate_only",
        "book_key": "tab",
        "edge_pp": 0.020600000000000007,
        "line": null,
        "market": "one_x_two",
        "side": "away"
      },
      {
        "actionability": "syndicate_only",
        "book_key": "unibet_fr",
        "edge_pp": 0.020399999999999974,
        "line": null,
        "market": "one_x_two",
        "side": "draw"
      },
      {
        "actionability": "syndicate_only",
        "book_key": "williamhill",
        "edge_pp": 0.020100000000000007,
        "line": 0.5,
        "market": "spreads",
        "side": "home"
      }
    ],
    "schema_version": "softbook_signals.0",
    "sharp_pick": null,
    "source": "SOFTBOOK_SIGNALS"
  },
  "softbook_spreads": {
    "benchmark": {
      "book": "pinnacle",
      "lines": [
        {
          "point": -0.75,
          "probabilities": {
            "away": 0.8136,
            "home": 0.1864
          }
        },
        {
          "point": -0.5,
          "probabilities": {
            "away": 0.7564,
            "home": 0.2436
          }
        },
        {
          "point": -0.25,
          "probabilities": {
            "away": 0.6989,
            "home": 0.3011
          }
        },
        {
          "point": 0.0,
          "probabilities": {
            "away": 0.6,
            "home": 0.4
          }
        },
        {
          "point": 0.25,
          "probabilities": {
            "away": 0.4482,
            "home": 0.5518
          }
        },
        {
          "point": 0.5,
          "probabilities": {
            "away": 0.3596,
            "home": 0.6404
          }
        },
        {
          "point": 0.75,
          "probabilities": {
            "away": 0.2914,
            "home": 0.7086
          }
        },
        {
          "point": 1.0,
          "probabilities": {
            "away": 0.2088,
            "home": 0.7912
          }
        },
        {
          "point": 1.25,
          "probabilities": {
            "away": 0.1885,
            "home": 0.8115
          }
        }
      ]
    },
    "books": [
      {
        "actionability": "syndicate_only",
        "book_key": "betonlineag",
        "lines": [
          {
            "edge_pp": {
              "away": 0.005500000000000005,
              "home": -0.00550000000000006
            },
            "point": 0.25,
            "probabilities": {
              "away": 0.4427,
              "home": 0.5573
            },
            "verdict": {
              "away": "NO_VALUE",
              "home": "NO_VALUE"
            }
          }
        ]
      },
      {
        "actionability": "syndicate_only",
        "book_key": "betrivers",
        "lines": [
          {
            "edge_pp": {
              "away": 0.013900000000000023,
              "home": -0.013899999999999996
            },
            "point": -0.75,
            "probabilities": {
              "away": 0.7997,
              "home": 0.2003
            },
            "verdict": {
              "away": "NO_VALUE",
              "home": "NO_VALUE"
            }
          },
          {
            "edge_pp": {
              "away": 0.016000000000000014,
              "home": -0.015999999999999986
            },
            "point": -0.5,
            "probabilities": {
              "away": 0.7404,
              "home": 0.2596
            },
            "verdict": {
              "away": "NO_VALUE",
              "home": "NO_VALUE"
            }
          },
          {
            "edge_pp": {
              "away": 0.014000000000000012,
              "home": -0.014000000000000012
            },
            "point": -0.25,
            "probabilities": {
              "away": 0.6849,
              "home": 0.3151
            },
            "verdict": {
              "away": "NO_VALUE",
              "home": "NO_VALUE"
            }
          },
          {
            "edge_pp": {
              "away": 0.0016999999999999793,
              "home": -0.0017000000000000348
            },
            "point": 0.25,
            "probabilities": {
              "away": 0.4465,
              "home": 0.5535
            },
            "verdict": {
              "away": "NO_VALUE",
              "home": "NO_VALUE"
            }
          },
          {
            "edge_pp": {
              "away": -0.0021000000000000463,
              "home": 0.0020999999999999908
            },
            "point": 0.5,
            "probabilities": {
              "away": 0.3617,
              "home": 0.6383
            },
            "verdict": {
              "away": "NO_VALUE",
              "home": "NO_VALUE"
            }
          },
          {
            "edge_pp": {
              "away": -0.0005000000000000004,
              "home": 0.000500000000000056
            },
            "point": 0.75,
            "probabilities": {
              "away": 0.2919,
              "home": 0.7081
            },
            "verdict": {
              "away": "NO_VALUE",
              "home": "NO_VALUE"
            }
          },
          {
            "edge_pp": {
              "away": -0.0016999999999999793,
              "home": 0.0017000000000000348
            },
            "point": 1.0,
            "probabilities": {
              "away": 0.2105,
              "home": 0.7895
            },
            "verdict": {
              "away": "NO_VALUE",
              "home": "NO_VALUE"
            }
          },
          {
            "edge_pp": {
              "away": -0.0010999999999999899,
              "home": 0.0010999999999999899
            },
            "point": 1.25,
            "probabilities": {
              "away": 0.1896,
              "home": 0.8104
            },
            "verdict": {
              "away": "NO_VALUE",
              "home": "NO_VALUE"
            }
          }
        ]
      },
      {
        "actionability": "syndicate_only",
        "book_key": "draftkings",
        "lines": [
          {
            "edge_pp": {
              "away": 0.019199999999999995,
              "home": -0.019199999999999995
            },
            "point": -0.25,
            "probabilities": {
              "away": 0.6797,
              "home": 0.3203
            },
            "verdict": {
              "away": "NO_VALUE",
              "home": "NO_VALUE"
            }
          },
          {
            "edge_pp": {
              "away": 0.011800000000000033,
              "home": -0.011799999999999977
            },
            "point": 0.0,
            "probabilities": {
              "away": 0.5882,
              "home": 0.4118
            },
            "verdict": {
              "away": "NO_VALUE",
              "home": "NO_VALUE"
            }
          },
          {
            "edge_pp": {
              "away": -0.0005999999999999894,
              "home": 0.0005999999999999339
            },
            "point": 0.25,
            "probabilities": {
              "away": 0.4488,
              "home": 0.5512
            },
            "verdict": {
              "away": "NO_VALUE",
              "home": "NO_VALUE"
            }
          },
          {
            "edge_pp": {
              "away": -0.010800000000000032,
              "home": 0.01079999999999992
            },
            "point": 0.5,
            "probabilities": {
              "away": 0.3704,
              "home": 0.6296
            },
            "verdict": {
              "away": "NO_VALUE",
              "home": "NO_VALUE"
            }
          }
        ]
      },
      {
        "actionability": "syndicate_only",
        "book_key": "gtbets",
        "lines": [
          {
            "edge_pp": {
              "away": -0.008700000000000041,
              "home": 0.00869999999999993
            },
            "point": 0.5,
            "probabilities": {
              "away": 0.3683,
              "home": 0.6317
            },
            "verdict": {
              "away": "NO_VALUE",
              "home": "NO_VALUE"
            }
          }
        ]
      },
      {
        "actionability": "syndicate_only",
        "book_key": "lowvig",
        "lines": [
          {
            "edge_pp": {
              "away": 0.005500000000000005,
              "home": -0.00550000000000006
            },
            "point": 0.25,
            "probabilities": {
              "away": 0.4427,
              "home": 0.5573
            },
            "verdict": {
              "away": "NO_VALUE",
              "home": "NO_VALUE"
            }
          }
        ]
      },
      {
        "actionability": "directly_actionable",
        "book_key": "matchbook",
        "lines": [
          {
            "edge_pp": {
              "away": 0.010399999999999965,
              "home": -0.010400000000000076
            },
            "point": 0.25,
            "probabilities": {
              "away": 0.4378,
              "home": 0.5622
            },
            "verdict": {
              "away": "NO_VALUE",
              "home": "NO_VALUE"
            }
          }
        ]
      },
      {
        "actionability": "syndicate_only",
        "book_key": "mybookieag",
        "lines": [
          {
            "edge_pp": {
              "away": 0.01990000000000003,
              "home": -0.019899999999999973
            },
            "point": 0.0,
            "probabilities": {
              "away": 0.5801,
              "home": 0.4199
            },
            "verdict": {
              "away": "NO_VALUE",
              "home": "NO_VALUE"
            }
          }
        ]
      },
      {
        "actionability": "syndicate_only",
        "book_key": "onexbet",
        "lines": [
          {
            "edge_pp": {
              "away": 0.018100000000000005,
              "home": -0.018100000000000005
            },
            "point": 0.0,
            "probabilities": {
              "away": 0.5819,
              "home": 0.4181
            },
            "verdict": {
              "away": "NO_VALUE",
              "home": "NO_VALUE"
            }
          },
          {
            "edge_pp": {
              "away": -0.011999999999999983,
              "home": 0.01200000000000001
            },
            "point": 1.0,
            "probabilities": {
              "away": 0.2208,
              "home": 0.7792
            },
            "verdict": {
              "away": "NO_VALUE",
              "home": "NO_VALUE"
            }
          }
        ]
      },
      {
        "actionability": "syndicate_only",
        "book_key": "tab",
        "lines": [
          {
            "edge_pp": {
              "away": 0.01869999999999994,
              "home": -0.018699999999999967
            },
            "point": -0.5,
            "probabilities": {
              "away": 0.7377,
              "home": 0.2623
            },
            "verdict": {
              "away": "NO_VALUE",
              "home": "NO_VALUE"
            }
          },
          {
            "edge_pp": {
              "away": 0.03420000000000001,
              "home": -0.03419999999999995
            },
            "point": 0.0,
            "probabilities": {
              "away": 0.5658,
              "home": 0.4342
            },
            "verdict": {
              "away": "VALUE",
              "home": "NO_VALUE"
            }
          },
          {
            "edge_pp": {
              "away": 0.023099999999999954,
              "home": -0.02310000000000001
            },
            "point": 0.5,
            "probabilities": {
              "away": 0.3365,
              "home": 0.6635
            },
            "verdict": {
              "away": "VALUE",
              "home": "NO_VALUE"
            }
          },
          {
            "edge_pp": {
              "away": 0.0011000000000000176,
              "home": -0.0010999999999999899
            },
            "point": 1.0,
            "probabilities": {
              "away": 0.2077,
              "home": 0.7923
            },
            "verdict": {
              "away": "NO_VALUE",
              "home": "NO_VALUE"
            }
          }
        ]
      },
      {
        "actionability": "syndicate_only",
        "book_key": "williamhill",
        "lines": [
          {
            "edge_pp": {
              "away": -0.020100000000000007,
              "home": 0.020100000000000007
            },
            "point": 0.5,
            "probabilities": {
              "away": 0.3797,
              "home": 0.6203
            },
            "verdict": {
              "away": "NO_VALUE",
              "home": "VALUE"
            }
          }
        ]
      }
    ],
    "capture_timestamp_utc": "2026-06-23T06:35:57.173263+00:00",
    "de_vig_method": "proportional",
    "execution_available": false,
    "fixture_key": "api_football:fixture:1489418",
    "operator_review_required": true,
    "output_status": "DISCOVERED",
    "period": "FULL_MATCH",
    "proof_scope": "WORLD_CUP_SOFTBOOK_SPREADS",
    "raw_prices_persisted": false,
    "request_cap": 1,
    "requests_attempted": 1,
    "requests_succeeded": 1,
    "schema_version": "softbook_spreads.0",
    "source": "THE_ODDS_API"
  },
  "softbook_totals": {
    "benchmark": {
      "book": "pinnacle",
      "lines": [
        {
          "point": 1.25,
          "probabilities": {
            "over": 0.7364,
            "under": 0.2636
          }
        },
        {
          "point": 1.5,
          "probabilities": {
            "over": 0.6754,
            "under": 0.3246
          }
        },
        {
          "point": 1.75,
          "probabilities": {
            "over": 0.6222,
            "under": 0.3778
          }
        },
        {
          "point": 2.0,
          "probabilities": {
            "over": 0.5479,
            "under": 0.4521
          }
        },
        {
          "point": 2.25,
          "probabilities": {
            "over": 0.4557,
            "under": 0.5443
          }
        },
        {
          "point": 2.5,
          "probabilities": {
            "over": 0.3913,
            "under": 0.6087
          }
        },
        {
          "point": 2.75,
          "probabilities": {
            "over": 0.3365,
            "under": 0.6635
          }
        },
        {
          "point": 3.0,
          "probabilities": {
            "over": 0.2725,
            "under": 0.7275
          }
        },
        {
          "point": 3.25,
          "probabilities": {
            "over": 0.2515,
            "under": 0.7485
          }
        }
      ]
    },
    "books": [
      {
        "actionability": "directly_actionable",
        "book_key": "betfair_ex_uk",
        "lines": [
          {
            "edge_pp": {
              "over": 0.007199999999999984,
              "under": -0.007199999999999984
            },
            "point": 1.5,
            "probabilities": {
              "over": 0.6682,
              "under": 0.3318
            },
            "verdict": {
              "over": "NO_VALUE",
              "under": "NO_VALUE"
            }
          },
          {
            "edge_pp": {
              "over": 0.0040000000000000036,
              "under": -0.0040000000000000036
            },
            "point": 2.5,
            "probabilities": {
              "over": 0.3873,
              "under": 0.6127
            },
            "verdict": {
              "over": "NO_VALUE",
              "under": "NO_VALUE"
            }
          }
        ]
      },
      {
        "actionability": "syndicate_only",
        "book_key": "betmgm",
        "lines": [
          {
            "edge_pp": {
              "over": 0.016900000000000026,
              "under": -0.016900000000000026
            },
            "point": 1.5,
            "probabilities": {
              "over": 0.6585,
              "under": 0.3415
            },
            "verdict": {
              "over": "NO_VALUE",
              "under": "NO_VALUE"
            }
          },
          {
            "edge_pp": {
              "over": -0.009700000000000042,
              "under": 0.009700000000000042
            },
            "point": 2.5,
            "probabilities": {
              "over": 0.401,
              "under": 0.599
            },
            "verdict": {
              "over": "NO_VALUE",
              "under": "NO_VALUE"
            }
          }
        ]
      },
      {
        "actionability": "syndicate_only",
        "book_key": "betonlineag",
        "lines": [
          {
            "edge_pp": {
              "over": 0.01040000000000002,
              "under": -0.010399999999999965
            },
            "point": 2.25,
            "probabilities": {
              "over": 0.4453,
              "under": 0.5547
            },
            "verdict": {
              "over": "NO_VALUE",
              "under": "NO_VALUE"
            }
          }
        ]
      },
      {
        "actionability": "syndicate_only",
        "book_key": "betrivers",
        "lines": [
          {
            "edge_pp": {
              "over": 0.006399999999999961,
              "under": -0.006400000000000017
            },
            "point": 1.5,
            "probabilities": {
              "over": 0.669,
              "under": 0.331
            },
            "verdict": {
              "over": "NO_VALUE",
              "under": "NO_VALUE"
            }
          },
          {
            "edge_pp": {
              "over": 0.01629999999999998,
              "under": -0.01629999999999998
            },
            "point": 2.5,
            "probabilities": {
              "over": 0.375,
              "under": 0.625
            },
            "verdict": {
              "over": "NO_VALUE",
              "under": "NO_VALUE"
            }
          }
        ]
      },
      {
        "actionability": "syndicate_only",
        "book_key": "casumo",
        "lines": [
          {
            "edge_pp": {
              "over": 0.01629999999999998,
              "under": -0.01629999999999998
            },
            "point": 2.5,
            "probabilities": {
              "over": 0.375,
              "under": 0.625
            },
            "verdict": {
              "over": "NO_VALUE",
              "under": "NO_VALUE"
            }
          }
        ]
      },
      {
        "actionability": "syndicate_only",
        "book_key": "codere_it",
        "lines": [
          {
            "edge_pp": {
              "over": -0.008600000000000052,
              "under": 0.008599999999999997
            },
            "point": 1.5,
            "probabilities": {
              "over": 0.684,
              "under": 0.316
            },
            "verdict": {
              "over": "NO_VALUE",
              "under": "NO_VALUE"
            }
          },
          {
            "edge_pp": {
              "over": -0.02400000000000002,
              "under": 0.02400000000000002
            },
            "point": 2.5,
            "probabilities": {
              "over": 0.4153,
              "under": 0.5847
            },
            "verdict": {
              "over": "NO_VALUE",
              "under": "VALUE"
            }
          }
        ]
      },
      {
        "actionability": "syndicate_only",
        "book_key": "coral",
        "lines": [
          {
            "edge_pp": {
              "over": 0.012700000000000045,
              "under": -0.012699999999999989
            },
            "point": 1.5,
            "probabilities": {
              "over": 0.6627,
              "under": 0.3373
            },
            "verdict": {
              "over": "NO_VALUE",
              "under": "NO_VALUE"
            }
          },
          {
            "edge_pp": {
              "over": -0.011300000000000032,
              "under": 0.011299999999999977
            },
            "point": 2.5,
            "probabilities": {
              "over": 0.4026,
              "under": 0.5974
            },
            "verdict": {
              "over": "NO_VALUE",
              "under": "NO_VALUE"
            }
          }
        ]
      },
      {
        "actionability": "syndicate_only",
        "book_key": "fanduel",
        "lines": [
          {
            "edge_pp": {
              "over": -0.02939999999999998,
              "under": 0.02939999999999998
            },
            "point": 1.5,
            "probabilities": {
              "over": 0.7048,
              "under": 0.2952
            },
            "verdict": {
              "over": "NO_VALUE",
              "under": "VALUE"
            }
          },
          {
            "edge_pp": {
              "over": -0.017400000000000027,
              "under": 0.01739999999999997
            },
            "point": 2.5,
            "probabilities": {
              "over": 0.4087,
              "under": 0.5913
            },
            "verdict": {
              "over": "NO_VALUE",
              "under": "NO_VALUE"
            }
          }
        ]
      },
      {
        "actionability": "syndicate_only",
        "book_key": "grosvenor",
        "lines": [
          {
            "edge_pp": {
              "over": 0.01629999999999998,
              "under": -0.01629999999999998
            },
            "point": 2.5,
            "probabilities": {
              "over": 0.375,
              "under": 0.625
            },
            "verdict": {
              "over": "NO_VALUE",
              "under": "NO_VALUE"
            }
          }
        ]
      },
      {
        "actionability": "syndicate_only",
        "book_key": "gtbets",
        "lines": [
          {
            "edge_pp": {
              "over": -0.016900000000000026,
              "under": 0.016900000000000026
            },
            "point": 2.5,
            "probabilities": {
              "over": 0.4082,
              "under": 0.5918
            },
            "verdict": {
              "over": "NO_VALUE",
              "under": "NO_VALUE"
            }
          }
        ]
      },
      {
        "actionability": "syndicate_only",
        "book_key": "ladbrokes_uk",
        "lines": [
          {
            "edge_pp": {
              "over": 0.016900000000000026,
              "under": -0.016900000000000026
            },
            "point": 1.5,
            "probabilities": {
              "over": 0.6585,
              "under": 0.3415
            },
            "verdict": {
              "over": "NO_VALUE",
              "under": "NO_VALUE"
            }
          },
          {
            "edge_pp": {
              "over": -0.011300000000000032,
              "under": 0.011299999999999977
            },
            "point": 2.5,
            "probabilities": {
              "over": 0.4026,
              "under": 0.5974
            },
            "verdict": {
              "over": "NO_VALUE",
              "under": "NO_VALUE"
            }
          }
        ]
      },
      {
        "actionability": "syndicate_only",
        "book_key": "leovegas",
        "lines": [
          {
            "edge_pp": {
              "over": 0.01629999999999998,
              "under": -0.01629999999999998
            },
            "point": 2.5,
            "probabilities": {
              "over": 0.375,
              "under": 0.625
            },
            "verdict": {
              "over": "NO_VALUE",
              "under": "NO_VALUE"
            }
          }
        ]
      },
      {
        "actionability": "syndicate_only",
        "book_key": "lowvig",
        "lines": [
          {
            "edge_pp": {
              "over": 0.01040000000000002,
              "under": -0.010399999999999965
            },
            "point": 2.25,
            "probabilities": {
              "over": 0.4453,
              "under": 0.5547
            },
            "verdict": {
              "over": "NO_VALUE",
              "under": "NO_VALUE"
            }
          }
        ]
      },
      {
        "actionability": "directly_actionable",
        "book_key": "matchbook",
        "lines": [
          {
            "edge_pp": {
              "over": 0.008199999999999985,
              "under": -0.008199999999999985
            },
            "point": 2.5,
            "probabilities": {
              "over": 0.3831,
              "under": 0.6169
            },
            "verdict": {
              "over": "NO_VALUE",
              "under": "NO_VALUE"
            }
          }
        ]
      },
      {
        "actionability": "syndicate_only",
        "book_key": "mybookieag",
        "lines": [
          {
            "edge_pp": {
              "over": -0.024699999999999944,
              "under": 0.0247
            },
            "point": 2.0,
            "probabilities": {
              "over": 0.5726,
              "under": 0.4274
            },
            "verdict": {
              "over": "NO_VALUE",
              "under": "VALUE"
            }
          }
        ]
      },
      {
        "actionability": "syndicate_only",
        "book_key": "onexbet",
        "lines": [
          {
            "edge_pp": {
              "over": 0.02180000000000004,
              "under": -0.021799999999999986
            },
            "point": 1.5,
            "probabilities": {
              "over": 0.6536,
              "under": 0.3464
            },
            "verdict": {
              "over": "VALUE",
              "under": "NO_VALUE"
            }
          },
          {
            "edge_pp": {
              "over": 0.011900000000000022,
              "under": -0.011900000000000022
            },
            "point": 2.0,
            "probabilities": {
              "over": 0.536,
              "under": 0.464
            },
            "verdict": {
              "over": "NO_VALUE",
              "under": "NO_VALUE"
            }
          },
          {
            "edge_pp": {
              "over": -0.006700000000000039,
              "under": 0.006700000000000039
            },
            "point": 2.5,
            "probabilities": {
              "over": 0.398,
              "under": 0.602
            },
            "verdict": {
              "over": "NO_VALUE",
              "under": "NO_VALUE"
            }
          },
          {
            "edge_pp": {
              "over": -0.006099999999999994,
              "under": 0.006099999999999994
            },
            "point": 3.0,
            "probabilities": {
              "over": 0.2786,
              "under": 0.7214
            },
            "verdict": {
              "over": "NO_VALUE",
              "under": "NO_VALUE"
            }
          }
        ]
      },
      {
        "actionability": "syndicate_only",
        "book_key": "paddypower",
        "lines": [
          {
            "edge_pp": {
              "over": -0.035699999999999954,
              "under": 0.03570000000000001
            },
            "point": 1.5,
            "probabilities": {
              "over": 0.7111,
              "under": 0.2889
            },
            "verdict": {
              "over": "NO_VALUE",
              "under": "VALUE"
            }
          },
          {
            "edge_pp": {
              "over": -0.04870000000000002,
              "under": 0.048699999999999966
            },
            "point": 2.5,
            "probabilities": {
              "over": 0.44,
              "under": 0.56
            },
            "verdict": {
              "over": "NO_VALUE",
              "under": "VALUE"
            }
          }
        ]
      },
      {
        "actionability": "syndicate_only",
        "book_key": "playup",
        "lines": [
          {
            "edge_pp": {
              "over": -0.024300000000000044,
              "under": 0.02429999999999999
            },
            "point": 2.5,
            "probabilities": {
              "over": 0.4156,
              "under": 0.5844
            },
            "verdict": {
              "over": "NO_VALUE",
              "under": "VALUE"
            }
          }
        ]
      },
      {
        "actionability": "syndicate_only",
        "book_key": "pmu_fr",
        "lines": [
          {
            "edge_pp": {
              "over": 0.012799999999999978,
              "under": -0.012800000000000034
            },
            "point": 2.5,
            "probabilities": {
              "over": 0.3785,
              "under": 0.6215
            },
            "verdict": {
              "over": "NO_VALUE",
              "under": "NO_VALUE"
            }
          }
        ]
      },
      {
        "actionability": "syndicate_only",
        "book_key": "skybet",
        "lines": [
          {
            "edge_pp": {
              "over": -0.012700000000000045,
              "under": 0.012699999999999989
            },
            "point": 1.5,
            "probabilities": {
              "over": 0.6881,
              "under": 0.3119
            },
            "verdict": {
              "over": "NO_VALUE",
              "under": "NO_VALUE"
            }
          },
          {
            "edge_pp": {
              "over": -0.019699999999999995,
              "under": 0.01970000000000005
            },
            "point": 2.5,
            "probabilities": {
              "over": 0.411,
              "under": 0.589
            },
            "verdict": {
              "over": "NO_VALUE",
              "under": "NO_VALUE"
            }
          }
        ]
      },
      {
        "actionability": "syndicate_only",
        "book_key": "tab",
        "lines": [
          {
            "edge_pp": {
              "over": 0.008700000000000041,
              "under": -0.008699999999999986
            },
            "point": 1.5,
            "probabilities": {
              "over": 0.6667,
              "under": 0.3333
            },
            "verdict": {
              "over": "NO_VALUE",
              "under": "NO_VALUE"
            }
          },
          {
            "edge_pp": {
              "over": -0.024300000000000044,
              "under": 0.02429999999999999
            },
            "point": 2.5,
            "probabilities": {
              "over": 0.4156,
              "under": 0.5844
            },
            "verdict": {
              "over": "NO_VALUE",
              "under": "VALUE"
            }
          }
        ]
      },
      {
        "actionability": "syndicate_only",
        "book_key": "tabtouch",
        "lines": [
          {
            "edge_pp": {
              "over": 0.01629999999999998,
              "under": -0.01629999999999998
            },
            "point": 2.5,
            "probabilities": {
              "over": 0.375,
              "under": 0.625
            },
            "verdict": {
              "over": "NO_VALUE",
              "under": "NO_VALUE"
            }
          }
        ]
      },
      {
        "actionability": "syndicate_only",
        "book_key": "unibet",
        "lines": [
          {
            "edge_pp": {
              "over": 0.01629999999999998,
              "under": -0.01629999999999998
            },
            "point": 2.5,
            "probabilities": {
              "over": 0.375,
              "under": 0.625
            },
            "verdict": {
              "over": "NO_VALUE",
              "under": "NO_VALUE"
            }
          }
        ]
      },
      {
        "actionability": "syndicate_only",
        "book_key": "unibet_nl",
        "lines": [
          {
            "edge_pp": {
              "over": 0.01629999999999998,
              "under": -0.01629999999999998
            },
            "point": 2.5,
            "probabilities": {
              "over": 0.375,
              "under": 0.625
            },
            "verdict": {
              "over": "NO_VALUE",
              "under": "NO_VALUE"
            }
          }
        ]
      },
      {
        "actionability": "syndicate_only",
        "book_key": "unibet_se",
        "lines": [
          {
            "edge_pp": {
              "over": 0.01629999999999998,
              "under": -0.01629999999999998
            },
            "point": 2.5,
            "probabilities": {
              "over": 0.375,
              "under": 0.625
            },
            "verdict": {
              "over": "NO_VALUE",
              "under": "NO_VALUE"
            }
          }
        ]
      },
      {
        "actionability": "syndicate_only",
        "book_key": "williamhill",
        "lines": [
          {
            "edge_pp": {
              "over": 0.008700000000000041,
              "under": -0.008699999999999986
            },
            "point": 1.5,
            "probabilities": {
              "over": 0.6667,
              "under": 0.3333
            },
            "verdict": {
              "over": "NO_VALUE",
              "under": "NO_VALUE"
            }
          },
          {
            "edge_pp": {
              "over": -0.019699999999999995,
              "under": 0.01970000000000005
            },
            "point": 2.5,
            "probabilities": {
              "over": 0.411,
              "under": 0.589
            },
            "verdict": {
              "over": "NO_VALUE",
              "under": "NO_VALUE"
            }
          }
        ]
      }
    ],
    "capture_timestamp_utc": "2026-06-23T06:35:57.046116+00:00",
    "de_vig_method": "proportional",
    "execution_available": false,
    "fixture_key": "api_football:fixture:1489418",
    "operator_review_required": true,
    "output_status": "DISCOVERED",
    "period": "FULL_MATCH",
    "proof_scope": "WORLD_CUP_SOFTBOOK_TOTALS",
    "raw_prices_persisted": false,
    "request_cap": 1,
    "requests_attempted": 1,
    "requests_succeeded": 1,
    "schema_version": "softbook_totals.0",
    "source": "THE_ODDS_API"
  },
  "spreads_kalshi": {
    "capture_timestamp_utc": "2026-06-23T06:35:58.544822+00:00",
    "de_vig_method": "proportional_kalshi",
    "execution_available": false,
    "fixture_key": "api_football:fixture:1489418",
    "lines": [
      {
        "away_cover_fair": 0.975,
        "home_cover_fair": 0.025,
        "line": -2.5
      },
      {
        "away_cover_fair": 0.92,
        "home_cover_fair": 0.08,
        "line": -1.5
      },
      {
        "away_cover_fair": 0.155,
        "home_cover_fair": 0.845,
        "line": 1.5
      },
      {
        "away_cover_fair": 0.055,
        "home_cover_fair": 0.945,
        "line": 2.5
      }
    ],
    "operator_review_required": true,
    "output_status": "DISCOVERED",
    "proof_scope": "WORLD_CUP_SPREADS_KALSHI_ANCHOR",
    "raw_prices_persisted": false,
    "request_cap": 1,
    "requests_attempted": 1,
    "requests_succeeded": 1,
    "schema_version": "spreads_kalshi.0",
    "source": "KALSHI"
  },
  "spreads_sharp": {
    "capture_timestamp_utc": "2026-06-23T06:35:56.448438+00:00",
    "de_vig_method": "proportional_pinnacle",
    "execution_available": false,
    "fixture_key": "api_football:fixture:1489418",
    "lines": [
      {
        "away_cover_fair": 0.8136,
        "home_cover_fair": 0.1864,
        "line": -0.75
      },
      {
        "away_cover_fair": 0.7564,
        "home_cover_fair": 0.2436,
        "line": -0.5
      },
      {
        "away_cover_fair": 0.6989,
        "home_cover_fair": 0.3011,
        "line": -0.25
      },
      {
        "away_cover_fair": 0.6,
        "home_cover_fair": 0.4,
        "line": 0.0
      },
      {
        "away_cover_fair": 0.4482,
        "home_cover_fair": 0.5518,
        "line": 0.25
      },
      {
        "away_cover_fair": 0.3596,
        "home_cover_fair": 0.6404,
        "line": 0.5
      },
      {
        "away_cover_fair": 0.2914,
        "home_cover_fair": 0.7086,
        "line": 0.75
      },
      {
        "away_cover_fair": 0.2088,
        "home_cover_fair": 0.7912,
        "line": 1.0
      },
      {
        "away_cover_fair": 0.1885,
        "home_cover_fair": 0.8115,
        "line": 1.25
      }
    ],
    "operator_review_required": true,
    "output_status": "DISCOVERED",
    "proof_scope": "WORLD_CUP_SPREADS_SHARP_ANCHOR",
    "raw_prices_persisted": false,
    "request_cap": 1,
    "requests_attempted": 1,
    "requests_succeeded": 1,
    "schema_version": "spreads_sharp.0",
    "source": "THE_ODDS_API"
  },
  "standings": {
    "execution_available": false,
    "fixture_key": "api_football:fixture:1489418",
    "group": "Group J",
    "operator_review_required": true,
    "output_status": "DISCOVERED",
    "proof_scope": "WORLD_CUP_GROUP_STANDINGS",
    "schema_version": "standings.0",
    "source": "API_FOOTBALL",
    "table": [
      {
        "draw": 0,
        "goal_diff": 5,
        "goals_against": 0,
        "goals_for": 5,
        "loss": 0,
        "played": 2,
        "points": 6,
        "rank": 1,
        "team": "Argentina",
        "win": 2
      },
      {
        "draw": 0,
        "goal_diff": 0,
        "goals_against": 3,
        "goals_for": 3,
        "loss": 1,
        "played": 2,
        "points": 3,
        "rank": 2,
        "team": "Austria",
        "win": 1
      },
      {
        "draw": 0,
        "goal_diff": -2,
        "goals_against": 4,
        "goals_for": 2,
        "loss": 1,
        "played": 2,
        "points": 3,
        "rank": 3,
        "team": "Algeria",
        "win": 1
      },
      {
        "draw": 0,
        "goal_diff": -3,
        "goals_against": 5,
        "goals_for": 2,
        "loss": 2,
        "played": 2,
        "points": 0,
        "rank": 4,
        "team": "Jordan",
        "win": 0
      }
    ]
  },
  "synthetics": {
    "constructions": {
      "ah_minus_0_25": {
        "away": {
          "edge_pp": 0.0023836066349255947,
          "kalshi_fair": 0.4423676012461059,
          "sharp_fair": 0.4447512078810315
        },
        "home": {
          "edge_pp": -0.004988489529547557,
          "kalshi_fair": 0.3052959501557633,
          "sharp_fair": 0.3003074606262157
        }
      },
      "dnb": {
        "away": {
          "edge_pp": 0.005267812026275909,
          "kalshi_fair": 0.5916666666666667,
          "sharp_fair": 0.5969344786929426
        },
        "home": {
          "edge_pp": -0.005267812026275964,
          "kalshi_fair": 0.40833333333333344,
          "sharp_fair": 0.4030655213070575
        }
      },
      "double_chance": {
        "away": {
          "edge_pp": 0.004481094527363005,
          "kalshi_fair": 0.7562189054726369,
          "sharp_fair": 0.7606999999999999
        },
        "home": {
          "edge_pp": -0.0011661691542289576,
          "kalshi_fair": 0.6467661691542289,
          "sharp_fair": 0.6456
        }
      }
    },
    "execution_available": false,
    "fixture_key": "api_football:fixture:1489418",
    "operator_review_required": true,
    "output_status": "DISCOVERED",
    "proof_scope": "WORLD_CUP_SYNTHETIC_CONSTRUCTIONS",
    "schema_version": "synthetics.0",
    "source": "DERIVED_1X2_SYNTHETICS"
  },
  "totals": {
    "execution_available": false,
    "fixture_key": "api_football:fixture:1489418",
    "operator_review_required": true,
    "output_status": "DISCOVERED",
    "proof_scope": "WORLD_CUP_TOTALS_COMPARISON",
    "schema_version": "totals.0",
    "shared_lines": [
      {
        "kalshi_over_fair": 0.685,
        "line": 1.5,
        "over_edge_pp": -0.009600000000000053,
        "sharp_over_fair": 0.6754
      },
      {
        "kalshi_over_fair": 0.385,
        "line": 2.5,
        "over_edge_pp": 0.006299999999999972,
        "sharp_over_fair": 0.3913
      }
    ],
    "source": "TOTALS_COMPARISON"
  },
  "totals_kalshi": {
    "capture_timestamp_utc": "2026-06-23T06:35:58.038884+00:00",
    "de_vig_method": "proportional_kalshi",
    "execution_available": false,
    "fixture_key": "api_football:fixture:1489418",
    "lines": [
      {
        "line": 0.5,
        "over_fair": 0.875,
        "under_fair": 0.125
      },
      {
        "line": 1.5,
        "over_fair": 0.685,
        "under_fair": 0.315
      },
      {
        "line": 2.5,
        "over_fair": 0.385,
        "under_fair": 0.615
      },
      {
        "line": 3.5,
        "over_fair": 0.205,
        "under_fair": 0.795
      },
      {
        "line": 4.5,
        "over_fair": 0.085,
        "under_fair": 0.915
      },
      {
        "line": 5.5,
        "over_fair": 0.03,
        "under_fair": 0.97
      }
    ],
    "operator_review_required": true,
    "output_status": "DISCOVERED",
    "proof_scope": "WORLD_CUP_TOTALS_KALSHI_ANCHOR",
    "raw_prices_persisted": false,
    "request_cap": 1,
    "requests_attempted": 1,
    "requests_succeeded": 1,
    "schema_version": "totals_kalshi.0",
    "source": "KALSHI"
  },
  "totals_sharp": {
    "capture_timestamp_utc": "2026-06-23T06:35:56.268953+00:00",
    "de_vig_method": "proportional_pinnacle",
    "execution_available": false,
    "fixture_key": "api_football:fixture:1489418",
    "lines": [
      {
        "line": 1.25,
        "over_fair": 0.7364,
        "under_fair": 0.2636
      },
      {
        "line": 1.5,
        "over_fair": 0.6754,
        "under_fair": 0.3246
      },
      {
        "line": 1.75,
        "over_fair": 0.6222,
        "under_fair": 0.3778
      },
      {
        "line": 2.0,
        "over_fair": 0.5479,
        "under_fair": 0.4521
      },
      {
        "line": 2.25,
        "over_fair": 0.4557,
        "under_fair": 0.5443
      },
      {
        "line": 2.5,
        "over_fair": 0.3913,
        "under_fair": 0.6087
      },
      {
        "line": 2.75,
        "over_fair": 0.3365,
        "under_fair": 0.6635
      },
      {
        "line": 3.0,
        "over_fair": 0.2725,
        "under_fair": 0.7275
      },
      {
        "line": 3.25,
        "over_fair": 0.2515,
        "under_fair": 0.7485
      }
    ],
    "operator_review_required": true,
    "output_status": "DISCOVERED",
    "proof_scope": "WORLD_CUP_TOTALS_SHARP_ANCHOR",
    "raw_prices_persisted": false,
    "request_cap": 1,
    "requests_attempted": 1,
    "requests_succeeded": 1,
    "schema_version": "totals_sharp.0",
    "source": "THE_ODDS_API"
  }
}
